controller_main/__init__.py
controller_main/controller_main_device_list.py
controller_main/controller_main_project_list.py
controller_main/controller_main_sms_record_list.py
controller_main/controller_main_sms_report_list.py
format_printer/__init__.py
format_printer/printer_controller_main.py
sms_client/__init__.py
sms_client/main.py
sms_client/settings.py
py_sms_cli-0.1.0.dist-info/METADATA
py_sms_cli-0.1.0.dist-info/WHEEL
py_sms_cli-0.1.0.dist-info/entry_points.txt
py_sms_cli-0.1.0.dist-info/top_level.txt
py_sms_cli-0.1.0.dist-info/RECORD
